[
            {
                "id": 0,
                "tag": "YOGURTS",
                "seccion": "Yogurts Helados",
                "nombre": "Yogurt Helado Mini",
                "precio": "$220",
                "descripcion": "Probando muchos caracteres",
                "urlImagen": "/img/delivery.jpg"
            },
            {
                "id": 1,
                "tag": "YOGURTS",
                "seccion": "YOGURTS",
                "nombre": "Yogurt Helado Chico",
                "precio": "$212",
                "descripcion": "probando muchos caracteres",
                "urlImagen": "img-1"
            }
        ]
